{
  "slug": "ecopower-energia-solar",
  "name": "Ecopower Energia Solar",
  "url_source": "https://encontresuafranquia.com.br/franquia/ecopower-energia-solar/",
  "scraped_at": "2026-04-30T23:30:21+00:00",
  "logo_url": "https://encontresuafranquia.com.br/wp-content/uploads/2026/01/ecopower-energia-solar.jpg",
  "description_short": "Ecopower Energia Solar oferece soluções inovadoras em energia renovável, destacando-se no setor por sua contribuição sustentável e eficiente.",
  "description_long": "A Ecopower Energia Solar é uma franquia que atua no setor de energia renovável, focando especificamente em soluções de energia solar. Este segmento tem ganhado destaque no Brasil devido à crescente demanda por fontes de energia sustentáveis e ao aumento da conscientização sobre os impactos ambientais das fontes tradicionais de energia. A energia solar, em particular, é vista como uma alternativa viável e econômica, especialmente em um país com alta incidência solar como o Brasil. A Ecopower Energia Solar tem se posicionado como uma facilitadora para indivíduos e empresas que desejam adotar essa tecnologia, oferecendo produtos e serviços que visam a eficiência energética e a redução de custos. Desde a sua fundação em 2013, a Ecopower Energia Solar tem se dedicado a desenvolver e implementar soluções de energia solar acessíveis e eficientes para uma ampla gama de clientes. Em 2019, a empresa decidiu expandir seu modelo de negócios através do franchising, permitindo que empreendedores locais se beneficiassem do crescente mercado de energia solar. A lógica de crescimento da marca baseia-se na capilaridade proporcionada pelas franquias, que permite alcançar diferentes regiões do país com eficiência e personalização no atendimento. A adoção do modelo de franquia reflete a estratégia da marca de ampliar sua presença no mercado e facilitar o acesso a tecnologias sustentáveis. A Ecopower Energia Solar oferece dois modelos de franquia: loja física e home based. Essa flexibilidade permite que investidores escolham o formato que melhor se adapta às suas necessidades e ao mercado local. O modelo de loja física é ideal para regiões com alta demanda, onde a presença física pode aumentar a visibilidade e a confiança do consumidor. Por outro lado, o formato home based oferece uma alternativa de menor custo inicial, permitindo que franqueados operem de maneira mais enxuta e com maior flexibilidade geográfica. Ambos os modelos são projetados para maximizar o retorno sobre o investimento, com prazos de retorno variando entre 6 e 12 meses, dependendo do formato escolhido. Sobre a franquia A Ecopower Energia Solar foi fundada em 2013 e iniciou seu modelo de franchising em 2019. Desde então, a empresa tem se concentrado em expandir sua rede de franquias por todo o Brasil, com uma estratégia de crescimento que visa tanto grandes centros urbanos quanto cidades de menor porte. A empresa se posiciona como líder no setor de energia solar no mercado brasileiro, destacando-se por oferecer soluções completas que vão desde a venda de equipamentos até a instalação e manutenção. A expansão contínua da marca reflete a crescente demanda por energia limpa e renovável no país. Modelo de negócio A franquia Ecopower Energia Solar opera oferecendo dois modelos principais: loja física e home based. No modelo de loja, os franqueados têm a oportunidade de estabelecer um ponto de venda fixo, que serve como um showroom para os produtos e serviços oferecidos. Este modelo é especialmente eficaz em áreas com alta densidade populacional e maior demanda por soluções de energia solar. Já no modelo home based, os franqueados operam sem a necessidade de um ponto comercial físico, o que reduz significativamente os custos operacionais e permite maior flexibilidade na operação. Ambos os modelos não cobram royalties nem taxas de publicidade, o que pode atrair investidores em busca de um retorno mais rápido. Perfil do público atendido O público-alvo da Ecopower Energia Solar inclui tanto consumidores residenciais quanto empresariais que buscam reduzir seus custos com energia elétrica e adotar práticas mais sustentáveis. Este perfil de consumidor está cada vez mais consciente dos benefícios ambientais e econômicos da energia solar. No Brasil, o segmento de energia solar tem crescido devido à abundância de luz solar e ao aumento das tarifas de energia elétrica, o que torna a adoção de sistemas solares uma alternativa atraente e viável para muitos. Estrutura da rede Atualmente, a rede de franquias da Ecopower Energia Solar conta com 330 unidades franqueadas espalhadas por diversas regiões do Brasil. Esta ampla rede permite que a empresa tenha uma presença significativa em diferentes mercados, adaptando suas ofertas às necessidades locais. A estratégia de expansão geográfica visa garantir que mais consumidores tenham acesso a soluções de energia solar, contribuindo para a popularização e democratização dessa tecnologia no país. Dados da Franquia",
  "founded_year": 2013,
  "franchise_start_year": 2019,
  "own_units": null,
  "franchised_units": 330,
  "total_units": 330,
  "min_investment": 17500,
  "max_investment": 76000,
  "investment_range_text": "R$ 17.500 / R$ 76.000",
  "franchise_fee": null,
  "franchise_fee_text": "Não informado",
  "working_capital": null,
  "working_capital_text": "Não informado",
  "investment_tier": "Até R$ 200 mil",
  "business_models": [
    {
      "tag": "loja",
      "royalties_text": "Não Cobra",
      "royalties_pct": 0.0,
      "royalties_base": null,
      "royalties_is_fixed": false,
      "ad_fee_text": "Não Cobra",
      "ad_fee_pct": 0.0,
      "ad_fee_base": null,
      "ad_fee_is_fixed": false,
      "avg_revenue_text": "Não informado",
      "avg_revenue": null,
      "avg_profit_text": "Não informado",
      "avg_profit": null,
      "payback_text": "9 a 12",
      "payback_min_months": 9,
      "payback_max_months": 12
    },
    {
      "tag": "home based",
      "royalties_text": "Não Cobra",
      "royalties_pct": 0.0,
      "royalties_base": null,
      "royalties_is_fixed": false,
      "ad_fee_text": "Não Cobra",
      "ad_fee_pct": 0.0,
      "ad_fee_base": null,
      "ad_fee_is_fixed": false,
      "avg_revenue_text": "Não informado",
      "avg_revenue": null,
      "avg_profit_text": "Não informado",
      "avg_profit": null,
      "payback_text": "6 a 12",
      "payback_min_months": 6,
      "payback_max_months": 12
    }
  ],
  "_quality_flags": {
    "has_logo": true,
    "has_description_long": true,
    "has_description_short": true,
    "has_investment": true,
    "has_units": true,
    "has_payback": true,
    "bm_count": 2,
    "fields_extracted": 12,
    "fields_total_known": 13,
    "fields_filled": 8,
    "fields_not_informed": [
      "Taxa de franquia",
      "Capital de giro",
      "Faturamento médio",
      "Lucro médio"
    ],
    "description_usable": true,
    "description_appears_templated": true,
    "layout_unrecognized": false,
    "has_corruption": false,
    "parser_flags": []
  },
  "_raw_fields": {
    "Fundação": "2013",
    "Início da franquia": "2019",
    "Unidades franqueadas": "330",
    "Investimento total": "R$ 17.500 / R$ 76.000",
    "Taxa de franquia": "Não informado",
    "Capital de giro": "Não informado",
    "Royalties": "Não Cobra (loja) / Não Cobra (home based)",
    "Taxa de publicidade": "Não Cobra (loja) / Não Cobra (home based)",
    "Faturamento médio": "Não informado",
    "Lucro médio": "Não informado",
    "Prazo de retorno (meses)": "9 a 12 (loja) / 6 a 12 (home based)",
    "Faixa de Investimento": "Franquias de Até R$ 200 mil"
  }
}