{
  "slug": "hiperfesta",
  "name": "Hiperfesta",
  "url_source": "https://encontresuafranquia.com.br/franquia/hiperfesta/",
  "scraped_at": "2026-04-30T23:30:21+00:00",
  "logo_url": "https://encontresuafranquia.com.br/wp-content/uploads/2026/01/hiperfesta.jpg",
  "description_short": "Hiperfesta é uma franquia de serviços para festas e eventos no Brasil, oferecendo ampla gama de produtos desde 2009 com destaque no mercado.",
  "description_long": "Hiperfesta é uma franquia estabelecida no setor de serviços, com foco em atender às diversas necessidades de festas e eventos no Brasil. Fundada em 2009, a empresa rapidamente se destacou no mercado por oferecer uma ampla gama de produtos e serviços voltados para celebrações, desde aniversários e casamentos até eventos corporativos. A marca se insere em um segmento dinâmico, que cresce impulsionado pela cultura brasileira de festejar e celebrar momentos especiais. Essa característica cultural, aliada à demanda constante por novidades e personalização, sustenta o crescimento contínuo da Hiperfesta. O modelo de franquia adotado pela Hiperfesta é um elemento chave de sua estratégia de expansão. Desde o início de sua operação de franchising, também em 2009, a marca tem se dedicado a estabelecer uma presença significativa em várias regiões do país. O sistema de franquias permite que empreendedores locais se beneficiem do know-how e da reputação da marca, ao mesmo tempo em que oferecem um serviço personalizado e adaptado às demandas de suas respectivas localidades. A lógica de crescimento da Hiperfesta se baseia na capacidade de replicar um modelo de negócio bem-sucedido, garantindo a qualidade e a padronização dos serviços prestados. O mercado de festas e eventos no Brasil é vasto e diversificado, abrangendo desde pequenas reuniões familiares até grandes festividades corporativas. A Hiperfesta se posiciona como uma solução completa para seus clientes, oferecendo desde artigos de decoração até serviços de buffet e animação. Este amplo portfólio é um diferencial competitivo, permitindo que a marca atenda a uma variedade de necessidades e preferências. A flexibilidade e a capacidade de adaptação são elementos essenciais que sustentam a relevância e a competitividade da Hiperfesta no mercado. Em termos gerais, o modelo de franquia da Hiperfesta é estruturado para facilitar a operação pelos franqueados, com suporte contínuo e treinamento especializado. Este suporte abrange desde a seleção de produtos até estratégias de marketing local, garantindo que cada unidade opere de forma eficaz e lucrativa. A taxa de royalties e a taxa de publicidade, calculadas com base no faturamento bruto das lojas, são mecanismos que asseguram a manutenção da qualidade e da imagem da marca em todas as suas unidades. Sobre a franquia Hiperfesta foi fundada em 2009 e, no mesmo ano, iniciou suas operações como franquia. A estratégia de expansão da marca se baseia na abertura de unidades franqueadas em diversas regiões do Brasil, buscando maximizar sua presença e atender a uma demanda crescente por serviços de festas e eventos. O posicionamento da Hiperfesta no mercado brasileiro é de uma marca confiável e inovadora, que combina tradição e modernidade para oferecer soluções completas e personalizadas para seus clientes. A expansão da rede é cuidadosamente planejada para garantir que cada nova unidade mantenha os padrões de qualidade e atendimento que caracterizam a marca. Modelo de negócio A operação da franquia Hiperfesta é centrada em unidades que oferecem uma ampla gama de produtos e serviços para festas e eventos. Esse modelo inclui a venda de artigos de decoração, serviços de buffet, animação e outros itens essenciais para a realização de eventos personalizados. A lógica operacional se baseia na combinação de um portfólio diversificado com a capacidade de personalização, permitindo que os franqueados atendam às necessidades específicas de seus mercados locais. A estrutura de suporte da franquia inclui treinamento contínuo e assistência em marketing, garantindo que cada unidade opere com eficiência e mantenha a reputação da marca. Perfil do público atendido O público-alvo da Hiperfesta é diversificado, abrangendo desde famílias que buscam celebrar datas especiais até empresas que organizam eventos corporativos. Este público valoriza a personalização e a qualidade dos serviços oferecidos, buscando soluções completas e práticas para suas necessidades de celebração. O segmento de festas e eventos no Brasil é impulsionado pela cultura de celebração presente no país, o que cria uma demanda constante por serviços inovadores e de qualidade, características que a Hiperfesta busca atender através de suas unidades franqueadas. Estrutura da rede A rede Hiperfesta é composta por 40 unidades próprias e 69 unidades franqueadas, resultando em uma presença significativa em diversas regiões do Brasil. Essa estrutura permite que a marca atinja um amplo público, oferecendo seus serviços em diferentes localidades e adaptando-se às especificidades de cada mercado. A expansão geográfica da Hiperfesta é um reflexo de sua estratégia de crescimento e do sucesso do modelo de franquia adotado, que permite a replicação eficaz de seu conceito de negócio em novas áreas. Dados da Franquia",
  "founded_year": 2009,
  "franchise_start_year": 2009,
  "own_units": 40,
  "franchised_units": 69,
  "total_units": 109,
  "min_investment": 360000,
  "max_investment": 360000,
  "investment_range_text": "R$ 360.000",
  "franchise_fee": null,
  "franchise_fee_text": "Não informado",
  "working_capital": null,
  "working_capital_text": "Não informado",
  "investment_tier": "Até R$ 500 mil",
  "business_models": [
    {
      "tag": "loja",
      "royalties_text": "3,00% - Fat. Bruto",
      "royalties_pct": 3.0,
      "royalties_base": "Fat. Bruto",
      "royalties_is_fixed": false,
      "ad_fee_text": "1,00% - Fat. Bruto",
      "ad_fee_pct": 1.0,
      "ad_fee_base": "Fat. Bruto",
      "ad_fee_is_fixed": false,
      "avg_revenue_text": "Não informado",
      "avg_revenue": null,
      "avg_profit_text": "Não informado",
      "avg_profit": null,
      "payback_text": "36 a 60",
      "payback_min_months": 36,
      "payback_max_months": 60
    }
  ],
  "_quality_flags": {
    "has_logo": true,
    "has_description_long": true,
    "has_description_short": true,
    "has_investment": true,
    "has_units": true,
    "has_payback": true,
    "bm_count": 1,
    "fields_extracted": 13,
    "fields_total_known": 13,
    "fields_filled": 9,
    "fields_not_informed": [
      "Taxa de franquia",
      "Capital de giro",
      "Faturamento médio",
      "Lucro médio"
    ],
    "description_usable": true,
    "description_appears_templated": true,
    "layout_unrecognized": false,
    "has_corruption": false,
    "parser_flags": []
  },
  "_raw_fields": {
    "Fundação": "2009",
    "Início da franquia": "2009",
    "Unidades próprias": "40",
    "Unidades franqueadas": "69",
    "Investimento total": "R$ 360.000",
    "Taxa de franquia": "Não informado",
    "Capital de giro": "Não informado",
    "Royalties": "3,00% - Fat. Bruto (loja)",
    "Taxa de publicidade": "1,00% - Fat. Bruto (loja)",
    "Faturamento médio": "Não informado",
    "Lucro médio": "Não informado",
    "Prazo de retorno (meses)": "36 a 60 (loja)",
    "Faixa de Investimento": "Franquias de Até R$ 500 mil"
  }
}