{
  "slug": "samsonite",
  "name": "Samsonite",
  "url_source": "https://encontresuafranquia.com.br/franquia/samsonite/",
  "scraped_at": "2026-04-30T23:30:22+00:00",
  "logo_url": "https://encontresuafranquia.com.br/wp-content/uploads/2026/01/samsonite.jpg",
  "description_short": "Qual o preço de uma franquia Samsonite? Saiba mais sobre o investimento na marca e outros detalhes aqui!",
  "description_long": "A Samsonite é uma marca renomada no segmento de moda, com foco especial em bolsas, mochilas e malas. Estabelecida em 1910, a empresa construiu uma reputação sólida ao longo de mais de um século, destacando-se pela qualidade e inovação de seus produtos. A marca é reconhecida mundialmente pela durabilidade e design dos seus produtos, o que a torna uma escolha popular entre os consumidores que buscam acessórios de viagem e uso diário de alta qualidade. Ao longo dos anos, a Samsonite se adaptou às mudanças no mercado, incorporando novas tecnologias e designs que atendem às necessidades dos consumidores modernos. O modelo de franquia da Samsonite foi introduzido em 2018, como parte de sua estratégia de expansão global e penetração em novos mercados. A decisão de franquear a marca permitiu à empresa aumentar sua presença geográfica sem comprometer a qualidade e a integridade da marca. As franquias oferecem aos empreendedores a oportunidade de se associarem a uma marca estabelecida e respeitada, com suporte contínuo em termos de marketing, treinamento e operações. A Samsonite busca expandir sua rede de franquias utilizando um modelo de negócio que equilibra inovação e tradição, garantindo que seus franqueados possam oferecer aos clientes uma experiência de compra consistente e de alta qualidade. No Brasil, a Samsonite se posiciona como uma opção de qualidade superior no segmento de acessórios pessoais, competindo com outras marcas de renome. A lógica de crescimento da empresa envolve a expansão de sua rede de franquias para captar uma fatia maior do mercado de acessórios, que está em constante crescimento devido ao aumento do turismo e das viagens a negócios. A marca se beneficia da crescente demanda por produtos que combinam funcionalidade e estilo, atendendo tanto a consumidores que priorizam a moda quanto aqueles que valorizam a praticidade e a durabilidade. A Samsonite continua a investir em pesquisa e desenvolvimento para manter sua posição de liderança no setor, oferecendo produtos que atendem às expectativas dos consumidores mais exigentes. Sobre a franquia A Samsonite foi fundada em 1910 e iniciou seu modelo de franquia em 2018. A estratégia de expansão da marca no Brasil envolve a abertura de novas unidades franqueadas para aumentar sua presença no mercado de acessórios pessoais e moda. A empresa se posiciona como uma marca premium, oferecendo produtos de alta qualidade que atendem às diversas necessidades dos consumidores. A expansão por meio de franquias permite à Samsonite manter um crescimento sustentável e alcançar um público mais amplo, enquanto continua a oferecer produtos inovadores e de alta qualidade. Modelo de negócio A franquia Samsonite opera com unidades que oferecem uma ampla gama de produtos, incluindo bolsas, mochilas e malas. As lojas são projetadas para proporcionar uma experiência de compra agradável, com um layout que destaca a qualidade e o design dos produtos. Os franqueados recebem suporte contínuo da empresa, incluindo treinamento em vendas e operações, além de assistência em marketing e publicidade. A lógica operacional da franquia é baseada na manutenção de altos padrões de qualidade e no fornecimento de produtos que atendem às expectativas dos consumidores em termos de durabilidade e estilo. Com uma taxa de royalties de 10% sobre as compras e uma taxa de publicidade de 4%, a Samsonite garante que seus franqueados tenham os recursos necessários para promover a marca de forma eficaz. Perfil do público atendido O público-alvo da Samsonite inclui consumidores que valorizam produtos de alta qualidade e design sofisticado. Este segmento é composto por viajantes frequentes, profissionais que necessitam de acessórios funcionais e estilosos, e pessoas que buscam durabilidade em seus produtos. No Brasil, o mercado de acessórios pessoais está em crescimento, impulsionado pelo aumento do turismo e da mobilidade urbana. A Samsonite atende a esses consumidores oferecendo produtos que combinam funcionalidade e estilo, características altamente valorizadas pelo público brasileiro. Estrutura da rede Atualmente, a Samsonite possui 16 unidades próprias e 40 unidades franqueadas. A rede de franquias está em expansão, buscando aumentar sua presença geográfica e alcançar novos mercados. A estrutura da rede permite que a Samsonite mantenha um controle de qualidade rigoroso, garantindo que todas as lojas ofereçam uma experiência de compra consistente e de alta qualidade aos consumidores. Dados da Franquia",
  "founded_year": 1910,
  "franchise_start_year": 2018,
  "own_units": 16,
  "franchised_units": 40,
  "total_units": 56,
  "min_investment": 560000,
  "max_investment": 760000,
  "investment_range_text": "R$ 560.000 / R$ 760.000",
  "franchise_fee": null,
  "franchise_fee_text": "Não informado",
  "working_capital": null,
  "working_capital_text": "Não informado",
  "investment_tier": "Até R$ 500 mil",
  "business_models": [
    {
      "tag": "loja",
      "royalties_text": "10,00% Compras",
      "royalties_pct": 10.0,
      "royalties_base": "Compras",
      "royalties_is_fixed": false,
      "ad_fee_text": "4,00% Compras",
      "ad_fee_pct": 4.0,
      "ad_fee_base": "Compras",
      "ad_fee_is_fixed": false,
      "avg_revenue_text": "Não informado",
      "avg_revenue": null,
      "avg_profit_text": "Não informado",
      "avg_profit": null,
      "payback_text": "48 a 60",
      "payback_min_months": 48,
      "payback_max_months": 60
    }
  ],
  "_quality_flags": {
    "has_logo": true,
    "has_description_long": true,
    "has_description_short": true,
    "has_investment": true,
    "has_units": true,
    "has_payback": true,
    "bm_count": 1,
    "fields_extracted": 13,
    "fields_total_known": 13,
    "fields_filled": 9,
    "fields_not_informed": [
      "Taxa de franquia",
      "Capital de giro",
      "Faturamento médio",
      "Lucro médio"
    ],
    "description_usable": true,
    "description_appears_templated": true,
    "layout_unrecognized": false,
    "has_corruption": false,
    "parser_flags": []
  },
  "_raw_fields": {
    "Fundação": "1910",
    "Início da franquia": "2018",
    "Unidades próprias": "16",
    "Unidades franqueadas": "40",
    "Investimento total": "R$ 560.000 / R$ 760.000",
    "Taxa de franquia": "Não informado",
    "Capital de giro": "Não informado",
    "Royalties": "10,00% Compras (loja)",
    "Taxa de publicidade": "4,00% Compras (loja)",
    "Faturamento médio": "Não informado",
    "Lucro médio": "Não informado",
    "Prazo de retorno (meses)": "48 a 60 (loja)",
    "Faixa de Investimento": "Franquias de Acima de R$ 500 mil"
  }
}